irtk/__init__.py
irtk/config.py
irtk/connector.py
irtk/io.py
irtk/loss.py
irtk/metric.py
irtk/model.py
irtk/parameter.py
irtk/renderer.py
irtk/sampling.py
irtk/scene.py
irtk/transform.py
irtk/utils.py
irtk/connectors/__init__.py
irtk/connectors/mitsuba_connector.py
irtk/connectors/nvdiffrast_connector.py
irtk/connectors/psdr_enzyme_connector.py
irtk/connectors/psdr_jit_connector.py
irtk/connectors/pytorch3d_connector.py
irtk/connectors/redner_connector.py
irtk/data/cubicL.txt
irtk-0.1.8.dist-info/WHEEL
irtk-0.1.8.dist-info/METADATA
irtk-0.1.8.dist-info/RECORD
