Metadata-Version: 2.1
Name: irtk
Version: 0.1.8
Summary: Inverse-Rendering Toolkit
Author-email: Guangyan Cai <gcai3@uci.edu>
Requires-Python: >=3.8
Requires-Dist: imageio >= 2.27.0
Requires-Dist: imageio_ffmpeg
Requires-Dist: numpy
Requires-Dist: gin-config
Requires-Dist: gpytoolbox
Requires-Dist: trimesh
Requires-Dist: matplotlib
Project-URL: Home, https://github.com/uci-rendering/inv-render-toolkit
